[
  { "id": 501, "hanja": "家", "meaning": "집", "sound": "가" },
  { "id": 502, "hanja": "給", "meaning": "줄", "sound": "급" },
  { "id": 503, "hanja": "千", "meaning": "일천", "sound": "천" },
  { "id": 504, "hanja": "兵", "meaning": "병마", "sound": "병" },
  { "id": 505, "hanja": "高", "meaning": "높을", "sound": "고" },
  { "id": 506, "hanja": "冠", "meaning": "곳갈", "sound": "관" },
  { "id": 507, "hanja": "陪", "meaning": "뫼실", "sound": "비" },
  { "id": 508, "hanja": "輦", "meaning": "년", "sound": "년" },
  { "id": 509, "hanja": "驅", "meaning": "몰", "sound": "구" },
  { "id": 510, "hanja": "轂", "meaning": "술위통", "sound": "곡" },
  { "id": 511, "hanja": "振", "meaning": "떨", "sound": "진" },
  { "id": 512, "hanja": "纓", "meaning": "긴", "sound": "영" },
  { "id": 513, "hanja": "世", "meaning": "인간", "sound": "세" },
  { "id": 514, "hanja": "祿", "meaning": "녹", "sound": "녹" },
  { "id": 515, "hanja": "侈", "meaning": "사치", "sound": "치" },
  { "id": 516, "hanja": "富", "meaning": "가며운", "sound": "부" },
  { "id": 517, "hanja": "車", "meaning": "술위", "sound": "거" },
  { "id": 518, "hanja": "駕", "meaning": "멍에", "sound": "가" },
  { "id": 519, "hanja": "肥", "meaning": "살질", "sound": "비" },
  { "id": 520, "hanja": "輕", "meaning": "가벼울", "sound": "경" },
  { "id": 521, "hanja": "策", "meaning": "막대", "sound": "측" },
  { "id": 522, "hanja": "功", "meaning": "공", "sound": "공" },
  { "id": 523, "hanja": "茂", "meaning": "거칠", "sound": "무" },
  { "id": 524, "hanja": "實", "meaning": "열매", "sound": "실" },
  { "id": 525, "hanja": "勒", "meaning": "굴에", "sound": "록" },
  { "id": 526, "hanja": "碑", "meaning": "비석", "sound": "비" },
  { "id": 527, "hanja": "刻", "meaning": "사길", "sound": "각" },
  { "id": 528, "hanja": "銘", "meaning": "새길", "sound": "명" },
  { "id": 529, "hanja": "磻", "meaning": "돌", "sound": "반" },
  { "id": 530, "hanja": "溪", "meaning": "시내", "sound": "계" },
  { "id": 531, "hanja": "伊", "meaning": "저", "sound": "이" },
  { "id": 532, "hanja": "尹", "meaning": "맏", "sound": "윤" },
  { "id": 533, "hanja": "佐", "meaning": "도울", "sound": "자" },
  { "id": 534, "hanja": "時", "meaning": "시절", "sound": "시" },
  { "id": 535, "hanja": "阿", "meaning": "언덕", "sound": "아" },
  { "id": 536, "hanja": "衡", "meaning": "저울대", "sound": "형" },
  { "id": 537, "hanja": "奄", "meaning": "문득", "sound": "엄" },
  { "id": 538, "hanja": "宅", "meaning": "집", "sound": "택" },
  { "id": 539, "hanja": "曲", "meaning": "굽을", "sound": "곡" },
  { "id": 540, "hanja": "阜", "meaning": "언덕", "sound": "부" },
  { "id": 541, "hanja": "微", "meaning": "적을", "sound": "미" },
  { "id": 542, "hanja": "旦", "meaning": "아침", "sound": "조" },
  { "id": 543, "hanja": "孰", "meaning": "누구", "sound": "숙" },
  { "id": 544, "hanja": "營", "meaning": "지을", "sound": "영" },
  { "id": 545, "hanja": "桓", "meaning": "굳셀", "sound": "환" },
  { "id": 546, "hanja": "公", "meaning": "공평", "sound": "공" },
  { "id": 547, "hanja": "匡", "meaning": "고칠", "sound": "광" },
  { "id": 548, "hanja": "合", "meaning": "모을", "sound": "합" },
  { "id": 549, "hanja": "濟", "meaning": "건널", "sound": "제" },
  { "id": 550, "hanja": "弱", "meaning": "약할", "sound": "약" },
  { "id": 551, "hanja": "扶", "meaning": "붙들", "sound": "부" },
  { "id": 552, "hanja": "傾", "meaning": "기울", "sound": "경" },
  { "id": 553, "hanja": "綺", "meaning": "비단", "sound": "기" },
  { "id": 554, "hanja": "廻", "meaning": "돌아올", "sound": "회" },
  { "id": 555, "hanja": "漢", "meaning": "한수", "sound": "한" },
  { "id": 556, "hanja": "惠", "meaning": "은혜", "sound": "혜" },
  { "id": 557, "hanja": "說", "meaning": "말할", "sound": "설" },
  { "id": 558, "hanja": "感", "meaning": "느낄", "sound": "감" },
  { "id": 559, "hanja": "武", "meaning": "굳셀", "sound": "무" },
  { "id": 560, "hanja": "丁", "meaning": "장정", "sound": "정" },
  { "id": 561, "hanja": "俊", "meaning": "뛰어날", "sound": "준" },
  { "id": 562, "hanja": "乂", "meaning": "어질", "sound": "예" },
  { "id": 563, "hanja": "密", "meaning": "빽빽할", "sound": "밀" },
  { "id": 564, "hanja": "勿", "meaning": "말", "sound": "물" },
  { "id": 565, "hanja": "多", "meaning": "많을", "sound": "다" },
  { "id": 566, "hanja": "士", "meaning": "선비", "sound": "사" },
  { "id": 567, "hanja": "寔", "meaning": "이", "sound": "식" },
  { "id": 568, "hanja": "寧", "meaning": "편안", "sound": "녕" },
  { "id": 569, "hanja": "晉", "meaning": "나라", "sound": "진" },
  { "id": 570, "hanja": "楚", "meaning": "나라", "sound": "초" },
  { "id": 571, "hanja": "更", "meaning": "고칠", "sound": "경" },
  { "id": 572, "hanja": "覇", "meaning": "으뜸", "sound": "패" },
  { "id": 573, "hanja": "趙", "meaning": "나라", "sound": "조" },
  { "id": 574, "hanja": "魏", "meaning": "나라", "sound": "위" },
  { "id": 575, "hanja": "困", "meaning": "괴로울", "sound": "곤" },
  { "id": 576, "hanja": "橫", "meaning": "비껴가다", "sound": "횡" },
  { "id": 577, "hanja": "假", "meaning": "빌릴", "sound": "가" },
  { "id": 578, "hanja": "途", "meaning": "길", "sound": "도" },
  { "id": 579, "hanja": "滅", "meaning": "꺼질", "sound": "멸" },
  { "id": 580, "hanja": "虢", "meaning": "나라", "sound": "괵" },
  { "id": 581, "hanja": "踐", "meaning": "밟을", "sound": "천" },
  { "id": 582, "hanja": "土", "meaning": "흙", "sound": "토" },
  { "id": 583, "hanja": "會", "meaning": "모을", "sound": "회" },
  { "id": 584, "hanja": "盟", "meaning": "맹세", "sound": "맹" },
  { "id": 585, "hanja": "何", "meaning": "어찌", "sound": "하" },
  { "id": 586, "hanja": "遵", "meaning": "좇을", "sound": "준" },
  { "id": 587, "hanja": "約", "meaning": "언약", "sound": "약" },
  { "id": 588, "hanja": "法", "meaning": "법", "sound": "법" },
  { "id": 589, "hanja": "韓", "meaning": "나라", "sound": "한" },
  { "id": 590, "hanja": "弊", "meaning": "해어질", "sound": "폐" },
  { "id": 591, "hanja": "煩", "meaning": "어지러울", "sound": "번" },
  { "id": 592, "hanja": "刑", "meaning": "형벌", "sound": "형" },
  { "id": 593, "hanja": "起", "meaning": "일어날", "sound": "기" },
  { "id": 594, "hanja": "翦", "meaning": "자를", "sound": "전" },
  { "id": 595, "hanja": "頗", "meaning": "자못", "sound": "파" },
  { "id": 596, "hanja": "牧", "meaning": "기를", "sound": "목" },
  { "id": 597, "hanja": "用", "meaning": "쓸", "sound": "용" },
  { "id": 598, "hanja": "軍", "meaning": "군사", "sound": "군" },
  { "id": 599, "hanja": "最", "meaning": "가장", "sound": "최" },
  { "id": 600, "hanja": "精", "meaning": "깨끗할", "sound": "정" },
  { "id": 601, "hanja": "宣", "meaning": "베풀", "sound": "선" },
  { "id": 602, "hanja": "威", "meaning": "위엄", "sound": "위" },
  { "id": 603, "hanja": "沙", "meaning": "모래", "sound": "사" },
  { "id": 604, "hanja": "漠", "meaning": "아득할", "sound": "막" },
  { "id": 605, "hanja": "馳", "meaning": "달릴", "sound": "치" },
  { "id": 606, "hanja": "譽", "meaning": "기릴", "sound": "예" },
  { "id": 607, "hanja": "丹", "meaning": "붉을", "sound": "단" },
  { "id": 608, "hanja": "靑", "meaning": "푸를", "sound": "청" },
  { "id": 609, "hanja": "九", "meaning": "아홉", "sound": "구" },
  { "id": 610, "hanja": "州", "meaning": "고을", "sound": "주" },
  { "id": 611, "hanja": "禹", "meaning": "임금", "sound": "우" },
  { "id": 612, "hanja": "跡", "meaning": "자취", "sound": "적" },
  { "id": 613, "hanja": "百", "meaning": "온", "sound": "백" },
  { "id": 614, "hanja": "郡", "meaning": "고을", "sound": "군" },
  { "id": 615, "hanja": "秦", "meaning": "나라", "sound": "진" },
  { "id": 616, "hanja": "幷", "meaning": "아우를", "sound": "병" },
  { "id": 617, "hanja": "嶽", "meaning": "높은 산", "sound": "악" },
  { "id": 618, "hanja": "宗", "meaning": "근본", "sound": "종" },
  { "id": 619, "hanja": "恒", "meaning": "항상", "sound": "항" },
  { "id": 620, "hanja": "岱", "meaning": "뫼", "sound": "대" },
  { "id": 621, "hanja": "禪", "meaning": "터닦을", "sound": "선" },
  { "id": 622, "hanja": "主", "meaning": "임금", "sound": "주" },
  { "id": 623, "hanja": "云", "meaning": "말할", "sound": "운" },
  { "id": 624, "hanja": "亭", "meaning": "정자", "sound": "정" },
  { "id": 625, "hanja": "雁", "meaning": "기러기", "sound": "안" },
  { "id": 626, "hanja": "門", "meaning": "문", "sound": "문" },
  { "id": 627, "hanja": "紫", "meaning": "붉을", "sound": "자" },
  { "id": 628, "hanja": "塞", "meaning": "막을", "sound": "색" },
  { "id": 629, "hanja": "鷄", "meaning": "닭", "sound": "계" },
  { "id": 630, "hanja": "田", "meaning": "밭", "sound": "전" },
  { "id": 631, "hanja": "赤", "meaning": "붉을", "sound": "적" },
  { "id": 632, "hanja": "城", "meaning": "성", "sound": "성" },
  { "id": 633, "hanja": "昆", "meaning": "맏", "sound": "곤" },
  { "id": 634, "hanja": "池", "meaning": "못", "sound": "지" },
  { "id": 635, "hanja": "碣", "meaning": "돌", "sound": "갈" },
  { "id": 636, "hanja": "石", "meaning": "돌", "sound": "석" },
  { "id": 637, "hanja": "鉅", "meaning": "강철", "sound": "거" },
  { "id": 638, "hanja": "野", "meaning": "들", "sound": "야" },
  { "id": 639, "hanja": "洞", "meaning": "골", "sound": "동" },
  { "id": 640, "hanja": "庭", "meaning": "뜰", "sound": "정" },
  { "id": 641, "hanja": "曠", "meaning": "빌", "sound": "광" },
  { "id": 642, "hanja": "遠", "meaning": "멀", "sound": "원" },
  { "id": 643, "hanja": "綿", "meaning": "이을", "sound": "면" },
  { "id": 644, "hanja": "邈", "meaning": "멀", "sound": "막" },
  { "id": 645, "hanja": "巖", "meaning": "바위", "sound": "암" },
  { "id": 646, "hanja": "岫", "meaning": "굴", "sound": "수" },
  { "id": 647, "hanja": "杳", "meaning": "아득할", "sound": "묘" },
  { "id": 648, "hanja": "冥", "meaning": "아득할", "sound": "명" },
  { "id": 649, "hanja": "治", "meaning": "다스릴", "sound": "치" },
  { "id": 650, "hanja": "本", "meaning": "밑바탕", "sound": "본" },
  { "id": 651, "hanja": "於", "meaning": "어", "sound": "어" },
  { "id": 652, "hanja": "農", "meaning": "농사", "sound": "농" },
  { "id": 653, "hanja": "務", "meaning": "힘쓸", "sound": "무" },
  { "id": 654, "hanja": "玆", "meaning": "이", "sound": "자" },
  { "id": 655, "hanja": "稼", "meaning": "심을", "sound": "가" },
  { "id": 656, "hanja": "穡", "meaning": "거둘", "sound": "색" },
  { "id": 657, "hanja": "俶", "meaning": "비로소", "sound": "숙" },
  { "id": 658, "hanja": "載", "meaning": "기록할", "sound": "재" },
  { "id": 659, "hanja": "南", "meaning": "앞", "sound": "남" },
  { "id": 660, "hanja": "畝", "meaning": "이랑", "sound": "묘" },
  { "id": 661, "hanja": "我", "meaning": "나", "sound": "아" },
  { "id": 662, "hanja": "藝", "meaning": "심을", "sound": "예" },
  { "id": 663, "hanja": "黍", "meaning": "기장", "sound": "서" },
  { "id": 664, "hanja": "稷", "meaning": "피", "sound": "직" },
  { "id": 665, "hanja": "稅", "meaning": "세금", "sound": "세" },
  { "id": 666, "hanja": "熟", "meaning": "익을", "sound": "숙" },
  { "id": 667, "hanja": "貢", "meaning": "바칠", "sound": "공" },
  { "id": 668, "hanja": "新", "meaning": "새", "sound": "신" },
  { "id": 669, "hanja": "勸", "meaning": "권할", "sound": "권" },
  { "id": 670, "hanja": "賞", "meaning": "줄", "sound": "상" },
  { "id": 671, "hanja": "黜", "meaning": "내칠", "sound": "출" },
  { "id": 672, "hanja": "陟", "meaning": "오를", "sound": "척" },
  { "id": 673, "hanja": "孟", "meaning": "맏", "sound": "맹" },
  { "id": 674, "hanja": "軻", "meaning": "술위", "sound": "가" },
  { "id": 675, "hanja": "敦", "meaning": "두터울", "sound": "돈" },
  { "id": 676, "hanja": "素", "meaning": "본디", "sound": "소" },
  { "id": 677, "hanja": "史", "meaning": "사기", "sound": "사" },
  { "id": 678, "hanja": "魚", "meaning": "고기", "sound": "어" },
  { "id": 679, "hanja": "秉", "meaning": "잡을", "sound": "병" },
  { "id": 680, "hanja": "直", "meaning": "곧을", "sound": "직" },
  { "id": 681, "hanja": "庶", "meaning": "여러", "sound": "서" },
  { "id": 682, "hanja": "幾", "meaning": "거의", "sound": "기" },
  { "id": 683, "hanja": "中", "meaning": "가운데", "sound": "중" },
  { "id": 684, "hanja": "庸", "meaning": "항상", "sound": "용" },
  { "id": 685, "hanja": "勞", "meaning": "힘쓸", "sound": "로" },
  { "id": 686, "hanja": "謙", "meaning": "겸손", "sound": "겸" },
  { "id": 687, "hanja": "謹", "meaning": "삼갈", "sound": "근" },
  { "id": 688, "hanja": "勅", "meaning": "경계", "sound": "칙" },
  { "id": 689, "hanja": "聆", "meaning": "들을", "sound": "령" },
  { "id": 690, "hanja": "音", "meaning": "소리", "sound": "음" },
  { "id": 691, "hanja": "察", "meaning": "살필", "sound": "찰" },
  { "id": 692, "hanja": "理", "meaning": "다스릴", "sound": "리" },
  { "id": 693, "hanja": "鑑", "meaning": "거울", "sound": "감" },
  { "id": 694, "hanja": "貌", "meaning": "얼굴", "sound": "모" },
  { "id": 695, "hanja": "辨", "meaning": "분별", "sound": "변" },
  { "id": 696, "hanja": "色", "meaning": "빛", "sound": "색" },
  { "id": 697, "hanja": "貽", "meaning": "끼칠", "sound": "이" },
  { "id": 698, "hanja": "厥", "meaning": "그", "sound": "궐" },
  { "id": 700, "hanja": "猷", "meaning": "꾀", "sound": "유" },
  { "id": 701, "hanja": "勉", "meaning": "힘쓸", "sound": "면" },
  { "id": 702, "hanja": "其", "meaning": "그", "sound": "기" },
  { "id": 703, "hanja": "祗", "meaning": "공경", "sound": "지" },
  { "id": 704, "hanja": "植", "meaning": "심을", "sound": "식" },
  { "id": 705, "hanja": "省", "meaning": "살필", "sound": "성" },
  { "id": 706, "hanja": "躬", "meaning": "몸", "sound": "궁" },
  { "id": 707, "hanja": "譏", "meaning": "나무랄", "sound": "기" },
  { "id": 708, "hanja": "誡", "meaning": "훈계", "sound": "계" },
  { "id": 709, "hanja": "寵", "meaning": "사랑", "sound": "총" },
  { "id": 710, "hanja": "增", "meaning": "더할", "sound": "증" },
  { "id": 711, "hanja": "抗", "meaning": "맞설", "sound": "항" },
  { "id": 712, "hanja": "極", "meaning": "다할", "sound": "극" },
  { "id": 713, "hanja": "殆", "meaning": "위태로울", "sound": "태" },
  { "id": 714, "hanja": "辱", "meaning": "욕될", "sound": "욕" },
  { "id": 715, "hanja": "近", "meaning": "가까울", "sound": "근" },
  { "id": 716, "hanja": "恥", "meaning": "부끄러울", "sound": "치" },
  { "id": 717, "hanja": "林", "meaning": "수풀", "sound": "림" },
  { "id": 718, "hanja": "睾", "meaning": "언덕", "sound": "고" },
  { "id": 719, "hanja": "幸", "meaning": "행여", "sound": "행" },
  { "id": 720, "hanja": "卽", "meaning": "곧", "sound": "즉" },
  { "id": 721, "hanja": "兩", "meaning": "두", "sound": "량" },
  { "id": 722, "hanja": "疎", "meaning": "멀", "sound": "소" },
  { "id": 723, "hanja": "見", "meaning": "볼", "sound": "견" },
  { "id": 724, "hanja": "机", "meaning": "틀", "sound": "기" },
  { "id": 725, "hanja": "解", "meaning": "풀", "sound": "해" },
  { "id": 726, "hanja": "組", "meaning": "끈", "sound": "조" },
  { "id": 727, "hanja": "誰", "meaning": "누구", "sound": "수" },
  { "id": 728, "hanja": "逼", "meaning": "박두할", "sound": "핍" },
  { "id": 729, "hanja": "索", "meaning": "찾을", "sound": "색" },
  { "id": 730, "hanja": "居", "meaning": "살", "sound": "거" },
  { "id": 731, "hanja": "閑", "meaning": "한가", "sound": "한" },
  { "id": 732, "hanja": "處", "meaning": "곳", "sound": "처" },
  { "id": 733, "hanja": "沈", "meaning": "잠길", "sound": "침" },
  { "id": 734, "hanja": "黙", "meaning": "잠잠할", "sound": "묵" },
  { "id": 735, "hanja": "寂", "meaning": "고요", "sound": "적" },
  { "id": 736, "hanja": "寥", "meaning": "고요", "sound": "료" },
  { "id": 737, "hanja": "求", "meaning": "구할", "sound": "구" },
  { "id": 738, "hanja": "古", "meaning": "옛", "sound": "고" },
  { "id": 739, "hanja": "尋", "meaning": "찾을", "sound": "심" },
  { "id": 740, "hanja": "論", "meaning": "말씀", "sound": "론" },
  { "id": 741, "hanja": "散", "meaning": "흩을", "sound": "산" },
  { "id": 742, "hanja": "慮", "meaning": "상념", "sound": "려" },
  { "id": 743, "hanja": "逍", "meaning": "노닐", "sound": "소" },
  { "id": 744, "hanja": "遙", "meaning": "노닐", "sound": "요" },
  { "id": 745, "hanja": "欣", "meaning": "기쁠", "sound": "흔" },
  { "id": 746, "hanja": "奏", "meaning": "아뢸", "sound": "주" },
  { "id": 747, "hanja": "累", "meaning": "허물", "sound": "루" },
  { "id": 748, "hanja": "遣", "meaning": "보낼", "sound": "견" },
  { "id": 749, "hanja": "戚", "meaning": "슬플", "sound": "척" },
  { "id": 750, "hanja": "謝", "meaning": "사례", "sound": "사" }
]
